pyresearch/ClassificationModule.py
pyresearch/ColorModule.py
pyresearch/FPS.py
pyresearch/FaceDetectionModule.py
pyresearch/FaceMeshModule.py
pyresearch/HandTrackingModule.py
pyresearch/PIDModule.py
pyresearch/PlotModule.py
pyresearch/PoseModule.py
pyresearch/SelfiSegmentationModule.py
pyresearch/SerialModule.py
pyresearch/Utils.py
pyresearch/__init__.py
pyresearch/heatmap_and_track.py
pyresearch/objectron.py
pyresearch-1.2.dist-info/LICENSE
pyresearch-1.2.dist-info/METADATA
pyresearch-1.2.dist-info/WHEEL
pyresearch-1.2.dist-info/top_level.txt
pyresearch-1.2.dist-info/RECORD
