Metadata-Version: 2.1
Name: pyresearch
Version: 1.2
Summary: Computer Vision Helping Library
Home-page: https://github.com/pyresearch/pyresearch.git
Author: pyresearch
Author-email: pyresearch0@gmail.com
License: MIT
Keywords: ComputerVision,HandTracking,FaceTracking,PoseEstimation
Classifier: Development Status :: 3 - Alpha
Classifier: Intended Audience :: Developers
Classifier: Topic :: Software Development :: Build Tools
Classifier: License :: OSI Approved :: MIT License
Classifier: Programming Language :: Python :: 3.6
Classifier: Programming Language :: Python :: 3.7
Classifier: Programming Language :: Python :: 3.8
Classifier: Programming Language :: Python :: 3.9
Classifier: Programming Language :: Python :: 3.10
License-File: LICENSE
Requires-Dist: opencv-python
Requires-Dist: numpy
Requires-Dist: supervision
Requires-Dist: ultralytics
Requires-Dist: mediapipe
